{"cameraMode":{"drawMode":0,"name":"Shaded","section":"Shading Mode"},"sceneLighting":true,"audioPlay":false,"sceneViewState":{"showFog":false,"showMaterialUpdate":false,"showSkybox":false,"showFlares":false,"showImageEffects":false,"showParticleSystems":true,"showVisualEffectGraphs":true,"m_FxEnabled":true},"in2DMode":false,"pivot":{"x":-130.4534912109375,"y":-119.01861572265625,"z":172.81597900390626},"rotation":{"x":-0.14647595584392548,"y":0.768079400062561,"z":-0.1894356906414032,"w":-0.5938965678215027},"size":290.1901550292969,"orthographic":false}